dummynet/__init__.py
dummynet/base58.py
dummynet/cgroups.py
dummynet/dummy_net.py
dummynet/errors.py
dummynet/host_shell.py
dummynet/namespace_shell.py
dummynet/process.py
dummynet/process_monitor.py
dummynet/run_info.py
dummynet/scoped.py
dummynet-10.0.0.dist-info/licenses/LICENSE.rst
dummynet-10.0.0.dist-info/METADATA
dummynet-10.0.0.dist-info/WHEEL
dummynet-10.0.0.dist-info/top_level.txt
dummynet-10.0.0.dist-info/RECORD
