Metadata-Version: 2.4
Name: dummynet
Version: 10.0.0
Summary: A tool for creating dummy networks using network namespaces.
Author-email: Steinwurf ApS <contact@steinwurf.com>
License-Expression: BSD-3-Clause
Project-URL: Homepage, https://github.com/steinwurf/dummynet
Project-URL: Repository, https://github.com/steinwurf/dummynet
Project-URL: Issues, https://github.com/steinwurf/dummynet/issues
Keywords: dummynet,network,namespace
Classifier: Development Status :: 5 - Production/Stable
Classifier: Environment :: Plugins
Classifier: Intended Audience :: Developers
Classifier: Operating System :: POSIX :: Linux
Classifier: Programming Language :: Python
Classifier: Programming Language :: Python :: 3
Classifier: Programming Language :: Python :: 3.11
Classifier: Programming Language :: Python :: 3.12
Classifier: Topic :: Software Development
Classifier: Topic :: Software Development :: Testing
Requires-Python: >=3.11
License-File: LICENSE.rst
Requires-Dist: psutil==7.0.0
Dynamic: license-file
